cloud.py
avilabsutils_cloud-0.0.3.dist-info/METADATA
avilabsutils_cloud-0.0.3.dist-info/WHEEL
avilabsutils_cloud-0.0.3.dist-info/entry_points.txt
avilabsutils_cloud-0.0.3.dist-info/top_level.txt
avilabsutils_cloud-0.0.3.dist-info/RECORD
