Metadata-Version: 2.1
Name: avilabsutils-cloud
Version: 0.0.3
Summary: A bunch of convienece public cloud tools.
Home-page: https://github.com/avilay/utils/cloud
Author: Avilay Parekh
Author-email: avilay@gmail.com
Classifier: Programming Language :: Python :: 3
Classifier: License :: OSI Approved :: MIT License
Classifier: Operating System :: OS Independent
Requires-Python: >=3.6
Requires-Dist: click
Requires-Dist: boto3
Requires-Dist: avilabsutils-cprint
Requires-Dist: avilabsutils-shell
